MANIFEST.in
README.txt
setup.cfg
setup.py
docs/HISTORY.txt
docs/INSTALL.txt
docs/LICENSE.GPL
docs/LICENSE.txt
quintagroup/__init__.py
quintagroup.formlib.captcha.egg-info/PKG-INFO
quintagroup.formlib.captcha.egg-info/SOURCES.txt
quintagroup.formlib.captcha.egg-info/dependency_links.txt
quintagroup.formlib.captcha.egg-info/entry_points.txt
quintagroup.formlib.captcha.egg-info/namespace_packages.txt
quintagroup.formlib.captcha.egg-info/not-zip-safe
quintagroup.formlib.captcha.egg-info/requires.txt
quintagroup.formlib.captcha.egg-info/top_level.txt
quintagroup/formlib/__init__.py
quintagroup/formlib/captcha/README.txt
quintagroup/formlib/captcha/__init__.py
quintagroup/formlib/captcha/configure.zcml
quintagroup/formlib/captcha/example.py
quintagroup/formlib/captcha/field.py
quintagroup/formlib/captcha/interfaces.py
quintagroup/formlib/captcha/version.txt
quintagroup/formlib/captcha/widget.py
quintagroup/formlib/captcha/tests/__init__.py
quintagroup/formlib/captcha/tests/test_doctests.py
quintagroup/formlib/captcha/tests/test_unittests.py
quintagroup/formlib/captcha/tests/tests.zcml